.releaserc
AUTHORS
CHANGELOG.md
ChangeLog
LICENSE
README.asciidoc
ROADMAP
package.json
requirements.txt
setup.cfg
setup.py
.circleci/config.yml
cryptopcash/__init__.py
cryptopcash/__main__.py
cryptopcash/cryptopcash.py
cryptopcash/util.py
cryptopcash.egg-info/PKG-INFO
cryptopcash.egg-info/SOURCES.txt
cryptopcash.egg-info/dependency_links.txt
cryptopcash.egg-info/entry_points.txt
cryptopcash.egg-info/not-zip-safe
cryptopcash.egg-info/pbr.json
cryptopcash.egg-info/requires.txt
cryptopcash.egg-info/top_level.txt
cryptopcash/market/CryptoCompare.py
cryptopcash/market/Market.py
cryptopcash/market/__init__.py
cryptopcash/model/Config.py
cryptopcash/model/Market.py
cryptopcash/model/Wallet.py
cryptopcash/model/__init__.py
cryptopcash/storage/LocalStorage.py
cryptopcash/storage/__init__.py
cryptopcash/ui/AddHoldingDialog.py
cryptopcash/ui/Asset.py
cryptopcash/ui/AssetsView.py
cryptopcash/ui/ErrorDialog.py
cryptopcash/ui/Header.py
cryptopcash/ui/Main.py
cryptopcash/ui/Popup.py
cryptopcash/ui/Title.py
cryptopcash/ui/TotalHolding.py
cryptopcash/ui/Value.py
cryptopcash/ui/__init__.py
images/colors.png
images/cryptopcash.png
resources/config/config.ini
tests/__init__.py
tests/conftest.py
tests/helper/__init__.py
tests/helper/cryptomarket.py
tests/helper/cryptopcash.py
tests/helper/storage.py
tests/unit/__init__.py
tests/unit/test_cryptopcash.py
tests/unit/market/test_CryptoCompare.py
tests/unit/model/test_Config.py
tests/unit/model/test_Market.py
tests/unit/model/test_Wallet.py
tests/unit/storage/__init__.py
tests/unit/storage/test_LocalStorage.py