Metadata-Version: 1.0
Name: cryptopcash
Version: 1.2.0
Summary: A cryptocurrency portfolio in cli
Home-page: UNKNOWN
Author: UNKNOWN
Author-email: UNKNOWN
License: UNKNOWN
Platform: UNKNOWN
